IPYNBreader/__init__.py
IPYNBreader/custom_exception.py
IPYNBreader/logger.py
IPYNBreader/site.py
IPYNBreader/youtube.py
IPYNBreader-0.0.1.dist-info/LICENSE
IPYNBreader-0.0.1.dist-info/METADATA
IPYNBreader-0.0.1.dist-info/WHEEL
IPYNBreader-0.0.1.dist-info/top_level.txt
IPYNBreader-0.0.1.dist-info/RECORD
